pyorit/__init__.py
pyorit/__main__.py
pyorit/connections.py
pyorit/loader.py
pyorit/utils.py
pyorit/version.py
pyorit/dB/__init__.py
pyorit/dB/core.py
pyorit/dB/database.py
pyorit/functions/_FastTelethon.py
pyorit/functions/__init__.py
pyorit/functions/all.py
pyorit/functions/antiflood_db.py
pyorit/functions/asst_fns.py
pyorit/functions/asstcmd_db.py
pyorit/functions/blacklist_chat_db.py
pyorit/functions/blacklist_db.py
pyorit/functions/botchat_db.py
pyorit/functions/broadcast_db.py
pyorit/functions/ch_db.py
pyorit/functions/chatBot_db.py
pyorit/functions/clean_db.py
pyorit/functions/echo_db.py
pyorit/functions/filter_db.py
pyorit/functions/forcesub_db.py
pyorit/functions/gban_mute_db.py
pyorit/functions/gcast_blacklist_db.py
pyorit/functions/google_image.py
pyorit/functions/greetings_db.py
pyorit/functions/logusers_db.py
pyorit/functions/mute_db.py
pyorit/functions/night_db.py
pyorit/functions/notes_db.py
pyorit/functions/nsfw_db.py
pyorit/functions/pmpermit_db.py
pyorit/functions/snips_db.py
pyorit/functions/sudos.py
pyorit/functions/vc_sudos.py
pyorit/functions/warn_db.py
pyorit/functions/ytdl.py
pyorit/misc/__init__.py
pyorit/misc/_assistant.py
pyorit/misc/_decorators.py
pyorit/misc/_supporter.py
pyorit/misc/_wrappers.py
pyorit-1.2.dist-info/LICENSE
pyorit-1.2.dist-info/METADATA
pyorit-1.2.dist-info/WHEEL
pyorit-1.2.dist-info/top_level.txt
pyorit-1.2.dist-info/RECORD
