Metadata-Version: 2.1
Name: pyorit
Version: 1.2
Summary: Library Userbot Telegram OrangIT 
Home-page: https://github.com/Projectgeez/Orang-IT/
Author: OrangIT
Author-email: zxce3@protonmail.com
License: GNU AFFERO GENERAL PUBLIC LICENSE (v3)
Platform: UNKNOWN
Classifier: Programming Language :: Python :: 3
Classifier: Programming Language :: Python :: 3.6
Classifier: Programming Language :: Python :: 3.7
Classifier: Programming Language :: Python :: 3.8
Classifier: Programming Language :: Python :: 3.9
Classifier: License :: OSI Approved :: GNU General Public License v3 (GPLv3)
Classifier: Operating System :: OS Independent
Requires-Python: >=3.6
License-File: LICENSE
Requires-Dist: redis
Requires-Dist: python-decouple (==3.3)
Requires-Dist: py-tgcalls (==0.5.2)
Requires-Dist: python-dotenv (==0.15.0)
Requires-Dist: cloudscraper
Requires-Dist: aiofiles
Requires-Dist: aiohttp
